{"1554": {"vote_id": "1554", "house": "H", "type": "floor_vote", "is_final": true, "yeas": ["Abbott", "Acton", "Albrecht", "Auxier", "Ballard", "Barlow", "Bolinder", "Brooks", "Burton", "Chevrier", "Chew", "Christofferson", "Clancy", "Defay", "Dunnigan", "Eliason", "Elison", "Fitisemanu", "Gricius", "Gwynn", "Hall", "Hawkins", "Ivory", "Jack", "Koford", "Kohler", "Kyle", "Lee", "Loubet", "Pherson", "Maloy", "Matthews", "Mauga", "Miller", "Monson", "Moss", "Nguyen", "Okerlund", "Owens", "Peck", "Petersen", "Peterson", "Peterson", "Peterson", "Pierucci", "Roberts", "Sawyer", "Schultz", "Shallenberger", "Shelley", "Shepherd", "Shipp", "Stoddard", "Strong", "Teuscher", "Thompson", "Thurston", "Walter", "Ward", "Watkins", "Welton", "Whyte", "Wilcox"], "nays": ["Bennion", "Dailey-Provost", "Dominguez", "Hayes", "Hollins", "Miller", "Moss", "Romero"], "yeas_count": 63, "nays_count": 8}, "2116": {"vote_id": "2116", "house": "S", "type": "floor_vote", "is_final": true, "yeas": ["Adams", "Balderree", "Fillmore", "Grover", "Harper", "Hinkins", "Ipson", "Cay", "Kell", "Musselman", "Owens", "Sandall", "Stevenson", "Stratton", "Thatcher", "Vickers", "Weiler", "Wilson", "Winterton"], "nays": ["Blouin", "Escamilla", "Kwan", "Pitcher", "Plumb", "Riebe"], "yeas_count": 19, "nays_count": 6}, "389": {"vote_id": "389", "house": "H", "type": "floor_vote", "is_final": true, "yeas": ["Abbott", "Acton", "Albrecht", "Auxier", "Ballard", "Barlow", "Bolinder", "Brooks", "Burton", "Chevrier", "Chew", "Christofferson", "Clancy", "Cutler", "Defay", "Dominguez", "Dunnigan", "Elison", "Fiefia", "Gricius", "Gwynn", "Hall", "Hawkins", "Ivory", "Jack", "Koford", "Kohler", "Kyle", "Lee", "Lisonbee", "Loubet", "Pherson", "Maloy", "Miller", "Monson", "Moss", "Moss", "Okerlund", "Peck", "Petersen", "Peterson", "Peterson", "Pierucci", "Roberts", "Sawyer", "Shelley", "Shepherd", "Shipp", "Snider", "Strong", "Teuscher", "Thompson", "Thurston", "Walter", "Ward", "Watkins", "Welton", "Whyte", "Wilcox"], "nays": ["Bennion", "Dailey-Provost", "Fitisemanu", "Hayes", "Hollins", "Matthews", "Mauga", "Nguyen", "Owens", "Romero"], "yeas_count": 59, "nays_count": 10}, "1977": {"vote_id": "1977", "house": "S", "type": "floor_vote", "is_final": true, "yeas": ["Adams", "Balderree", "Brammer", "Fillmore", "Hinkins", "Ipson", "Johnson", "Kwan", "Cay", "Musselman", "Riebe", "Stevenson", "Stratton", "Thatcher", "Vickers", "Weiler", "Wilson", "Winterton"], "nays": ["Blouin"], "yeas_count": 18, "nays_count": 1}}