{"148": {"vote_id": "148", "house": "H", "type": "floor_vote", "is_final": true, "yeas": ["Abbott", "Acton", "Albrecht", "Auxier", "Ballard", "Barlow", "Bolinder", "Brooks", "Burton", "Chevrier", "Chew", "Christofferson", "Clancy", "Cutler", "Dailey-Provost", "Defay", "Dunnigan", "Eliason", "Elison", "Fiefia", "Fitisemanu", "Gricius", "Gwynn", "Hall", "Hawkins", "Ivory", "Jack", "Koford", "Kohler", "Kyle", "Lee", "Lisonbee", "Loubet", "Pherson", "Maloy", "Matthews", "Mauga", "Miller", "Monson", "Okerlund", "Peck", "Petersen", "Peterson", "Peterson", "Pierucci", "Roberts", "Sawyer", "Schultz", "Shallenberger", "Shelley", "Shepherd", "Shipp", "Snider", "Stoddard", "Strong", "Thompson", "Thurston", "Walter", "Ward", "Watkins", "Welton", "Whyte", "Wilcox"], "nays": ["Bennion", "Dominguez", "Hayes", "Hollins", "Miller", "Moss", "Nguyen", "Owens", "Romero"], "yeas_count": 63, "nays_count": 9}, "1187": {"vote_id": "1187", "house": "H", "type": "floor_vote", "is_final": true, "yeas": ["Abbott", "Acton", "Albrecht", "Ballard", "Barlow", "Bolinder", "Brooks", "Burton", "Chevrier", "Chew", "Christofferson", "Clancy", "Cutler", "Dailey-Provost", "Defay", "Dunnigan", "Eliason", "Elison", "Fiefia", "Gricius", "Gwynn", "Hall", "Hawkins", "Hayes", "Ivory", "Jack", "Koford", "Kohler", "Kyle", "Lee", "Lisonbee", "Loubet", "Pherson", "Maloy", "Matthews", "Mauga", "Miller", "Monson", "Moss", "Okerlund", "Peck", "Petersen", "Peterson", "Peterson", "Peterson", "Pierucci", "Roberts", "Sawyer", "Schultz", "Shallenberger", "Shelley", "Shepherd", "Shipp", "Snider", "Stoddard", "Strong", "Teuscher", "Thompson", "Thurston", "Walter", "Ward", "Watkins", "Welton", "Whyte", "Wilcox"], "nays": ["Bennion", "Dominguez", "Fitisemanu", "Hollins", "Miller", "Moss", "Nguyen", "Owens", "Romero"], "yeas_count": 65, "nays_count": 9}, "1618": {"vote_id": "1618", "house": "S", "type": "floor_vote", "is_final": true, "yeas": ["Adams", "Balderree", "Cullimore", "Fillmore", "Grover", "Harper", "Hinkins", "Ipson", "Johnson", "Cay", "Millner", "Musselman", "Owens", "Sandall", "Stevenson", "Stratton", "Thatcher", "Vickers", "Weiler", "Wilson", "Winterton"], "nays": ["Blouin", "Escamilla", "Kwan", "Pitcher", "Riebe"], "yeas_count": 21, "nays_count": 5}, "1229": {"vote_id": "1229", "house": "S", "type": "floor_vote", "is_final": true, "yeas": ["Balderree", "Brammer", "Fillmore", "Harper", "Hinkins", "Ipson", "Johnson", "Cay", "Millner", "Musselman", "Owens", "Stratton", "Vickers", "Wilson", "Winterton"], "nays": ["Blouin", "Kwan", "Pitcher", "Plumb", "Riebe"], "yeas_count": 15, "nays_count": 5}}