{"957": {"vote_id": "957", "house": "S", "type": "floor_vote", "is_final": true, "yeas": ["Adams", "Balderree", "Blouin", "Cullimore", "Escamilla", "Grover", "Harper", "Hinkins", "Ipson", "Johnson", "Kwan", "Cay", "Millner", "Musselman", "Owens", "Pitcher", "Plumb", "Riebe", "Stevenson", "Stratton", "Thatcher", "Vickers", "Weiler", "Wilson", "Winterton"], "nays": ["Fillmore"], "yeas_count": 25, "nays_count": 1}, "326": {"vote_id": "326", "house": "S", "type": "floor_vote", "is_final": true, "yeas": ["Balderree", "Blouin", "Brammer", "Escamilla", "Fillmore", "Hinkins", "Ipson", "Johnson", "Kwan", "Cay", "Kell", "Millner", "Musselman", "Owens", "Pitcher", "Plumb", "Riebe", "Sandall", "Stevenson", "Thatcher", "Vickers", "Weiler", "Wilson", "Winterton"], "nays": [], "yeas_count": 24, "nays_count": 0}, "1383": {"vote_id": "1383", "house": "H", "type": "floor_vote", "is_final": true, "yeas": ["Abbott", "Acton", "Albrecht", "Auxier", "Ballard", "Barlow", "Bennion", "Bolinder", "Brooks", "Burton", "Chew", "Christofferson", "Clancy", "Cutler", "Dailey-Provost", "Defay", "Dunnigan", "Eliason", "Elison", "Fiefia", "Fitisemanu", "Gricius", "Gwynn", "Hall", "Hawkins", "Hayes", "Hollins", "Ivory", "Jack", "Koford", "Kohler", "Kyle", "Lee", "Lisonbee", "Loubet", "Maloy", "Matthews", "Miller", "Miller", "Monson", "Moss", "Moss", "Nguyen", "Okerlund", "Owens", "Peck", "Petersen", "Peterson", "Peterson", "Peterson", "Pierucci", "Roberts", "Romero", "Sawyer", "Shallenberger", "Shelley", "Shepherd", "Shipp", "Snider", "Stoddard", "Strong", "Teuscher", "Thompson", "Thurston", "Walter", "Ward", "Watkins", "Welton", "Whyte", "Wilcox"], "nays": [], "yeas_count": 70, "nays_count": 0}}