{"1566": {"vote_id": "1566", "house": "S", "type": "floor_vote", "is_final": true, "yeas": ["Adams", "Balderree", "Blouin", "Brammer", "Escamilla", "Fillmore", "Grover", "Harper", "Hinkins", "Ipson", "Johnson", "Kwan", "Kell", "Millner", "Musselman", "Owens", "Plumb", "Riebe", "Sandall", "Stevenson", "Stratton", "Thatcher", "Vickers", "Weiler", "Wilson", "Winterton"], "nays": [], "yeas_count": 26, "nays_count": 0}, "1511": {"vote_id": "1511", "house": "S", "type": "floor_vote", "is_final": true, "yeas": ["Adams", "Balderree", "Blouin", "Brammer", "Escamilla", "Harper", "Hinkins", "Ipson", "Johnson", "Kwan", "Cay", "Millner", "Musselman", "Owens", "Plumb", "Riebe", "Sandall", "Stevenson", "Stratton", "Thatcher", "Weiler", "Wilson", "Winterton"], "nays": [], "yeas_count": 23, "nays_count": 0}, "1476": {"vote_id": "1476", "house": "H", "type": "floor_vote", "is_final": true, "yeas": ["Abbott", "Acton", "Albrecht", "Auxier", "Ballard", "Barlow", "Bennion", "Bolinder", "Brooks", "Burton", "Chevrier", "Chew", "Christofferson", "Cutler", "Dailey-Provost", "Defay", "Dominguez", "Dunnigan", "Eliason", "Elison", "Fiefia", "Fitisemanu", "Gricius", "Gwynn", "Hall", "Hawkins", "Hayes", "Hollins", "Ivory", "Jack", "Koford", "Kohler", "Kyle", "Lee", "Loubet", "Pherson", "Maloy", "Matthews", "Mauga", "Miller", "Miller", "Monson", "Moss", "Nguyen", "Okerlund", "Owens", "Peck", "Petersen", "Peterson", "Peterson", "Peterson", "Roberts", "Romero", "Sawyer", "Schultz", "Shallenberger", "Shelley", "Shepherd", "Shipp", "Stoddard", "Strong", "Teuscher", "Thompson", "Thurston", "Walter", "Ward", "Watkins", "Welton", "Whyte", "Wilcox"], "nays": [], "yeas_count": 70, "nays_count": 0}}